README.rst
setup.py
django_ecl_tools.egg-info/PKG-INFO
django_ecl_tools.egg-info/SOURCES.txt
django_ecl_tools.egg-info/dependency_links.txt
django_ecl_tools.egg-info/top_level.txt
ecl_tools/__init__.py
ecl_tools/bulkmail/__init__.py
ecl_tools/bulkmail/admin.py
ecl_tools/bulkmail/forms.py
ecl_tools/bulkmail/models.py
ecl_tools/bulkmail/tasks.py
ecl_tools/bulkmail/tests.py
ecl_tools/bulkmail/urls.py
ecl_tools/bulkmail/views.py
ecl_tools/bulkmail/mailers/__init__.py
ecl_tools/bulkmail/mailers/base.py
ecl_tools/bulkmail/mailers/mailgun.py
ecl_tools/bulkmail/management/__init__.py
ecl_tools/bulkmail/management/commands/__init__.py
ecl_tools/bulkmail/management/commands/bucket.py
ecl_tools/bulkmail/management/commands/dups.py
ecl_tools/bulkmail/management/commands/import_list.py
ecl_tools/bulkmail/management/commands/pull_events.py
ecl_tools/bulkmail/migrations/0001_initial.py
ecl_tools/bulkmail/migrations/0002_auto_20150520_1834.py
ecl_tools/bulkmail/migrations/__init__.py
ecl_tools/bulkmail/resolvers/__init__.py
ecl_tools/bulkmail/resolvers/example.py
ecl_tools/config/__init__.py
ecl_tools/config/admin.py
ecl_tools/config/autoconf.py
ecl_tools/config/models.py
ecl_tools/config/tests.py
ecl_tools/config/views.py
ecl_tools/config/middleware/__init__.py
ecl_tools/config/middleware/conf.py
ecl_tools/config/templatetags/__init__.py
ecl_tools/config/templatetags/tags.py
ecl_tools/mail/__init__.py
ecl_tools/mail/admin.py
ecl_tools/mail/admin_views.py
ecl_tools/mail/core.py
ecl_tools/mail/cron.py
ecl_tools/mail/models.py
ecl_tools/mail/tests.py
ecl_tools/mail/migrations/0001_initial.py
ecl_tools/mail/migrations/0002_auto__add_smsmessage.py
ecl_tools/mail/migrations/__init__.py
ecl_tools/security/__init__.py
ecl_tools/security/middleware/__init__.py
ecl_tools/security/middleware/auth.py
ecl_tools/security/middleware/security.py
ecl_tools/utils/__init__.py
ecl_tools/utils/admin.py
ecl_tools/utils/context_processors.py
ecl_tools/utils/models.py
ecl_tools/utils/tests.py
ecl_tools/utils/views.py
ecl_tools/utils/widgets.py
ecl_tools/utils/management/__init__.py
ecl_tools/utils/management/commands/__init__.py
