Metadata-Version: 1.0
Name: django-ecl-tools
Version: 0.1.5
Summary: EdgeCaseLabs' Django Tools
Home-page: http://EdgeCaseLabs.com
Author: Edge Case Labs, LLC
Author-email: software@edgecaselabs.com
License: YMMV
Platform: UNKNOWN
